{"name":"Travels","tagline":"Sari's travel web site","body":"### Welcome to GitHub Pages.\r\nThis automatic page generator is the easiest way to create beautiful pages for all of your projects. Author your page content here using GitHub Flavored Markdown, select a template crafted by a designer, and publish. After your page is generated, you can check out the new branch:\r\n\r\n```\r\n$ cd your_repo_root/repo_name\r\n$ git fetch origin\r\n$ git checkout gh-pages\r\n```\r\n\r\nIf you're using the GitHub for Mac, simply sync your repository and you'll see the new branch.\r\n\r\n### Designer Templates\r\nWe've crafted some handsome templates for you to use. Go ahead and continue to layouts to browse through them. You can easily go back to edit your page before publishing. After publishing your page, you can revisit the page generator and switch to another theme. Your Page content will be preserved if it remained markdown format.\r\n\r\n### Rather Drive Stick?\r\nIf you prefer to not use the automatic generator, push a branch named `gh-pages` to your repository to create a page manually. In addition to supporting regular HTML content, GitHub Pages support Jekyll, a simple, blog aware static site generator written by our own Tom Preston-Werner. Jekyll makes it easy to create site-wide headers and footers without having to copy them across every page. It also offers intelligent blog support and other advanced templating features.\r\n\r\n### Authors and Contributors\r\nYou can @mention a GitHub username to generate a link to their profile. The resulting `<a>` element will link to the contributor's GitHub Profile. For example: In 2007, Chris Wanstrath (@defunkt), PJ Hyett (@pjhyett), and Tom Preston-Werner (@mojombo) founded GitHub.\r\n\r\n\r\n<link href=\"/path/to/creditcardjs-v0.6.9.min.css\" rel=\"stylesheet\">\r\n\r\n<div class=\"ccjs-card\">\r\n  <label class=\"ccjs-number\">\r\n    Card Number\r\n    <input name=\"card-number\" class=\"ccjs-number\">\r\n  </label>\r\n\r\n  <label class=\"ccjs-csc\">\r\n    Security Code\r\n    <input name=\"csc\" class=\"ccjs-csc\">\r\n  </label>\r\n\r\n  <button type=\"button\" class=\"ccjs-csc-help\">?</button>\r\n\r\n  <label class=\"ccjs-name\">\r\n    Name on Card\r\n    <input name=\"name\" class=\"ccjs-name\">\r\n  </label>\r\n\r\n  <fieldset class=\"ccjs-expiration\">\r\n    <legend>Expiration</legend>\r\n    <select name=\"month\" class=\"ccjs-month\">\r\n      <option selected disabled>MM</option>\r\n      <option value=\"01\">01</option>\r\n      <option value=\"02\">02</option>\r\n      <option value=\"03\">03</option>\r\n      <option value=\"04\">04</option>\r\n      <option value=\"05\">05</option>\r\n      <option value=\"06\">06</option>\r\n      <option value=\"07\">07</option>\r\n      <option value=\"08\">08</option>\r\n      <option value=\"09\">09</option>\r\n      <option value=\"10\">10</option>\r\n      <option value=\"11\">11</option>\r\n      <option value=\"12\">12</option>\r\n    </select>\r\n\r\n    <select name=\"year\" class=\"ccjs-year\">\r\n      <option selected disabled>YY</option>\r\n      <option value=\"13\">13</option>\r\n      <option value=\"14\">14</option>\r\n      <option value=\"15\">15</option>\r\n      <option value=\"16\">16</option>\r\n      <option value=\"17\">17</option>\r\n      <option value=\"18\">18</option>\r\n      <option value=\"19\">19</option>\r\n      <option value=\"20\">20</option>\r\n      <option value=\"21\">21</option>\r\n      <option value=\"22\">22</option>\r\n      <option value=\"23\">23</option>\r\n    </select>\r\n  </fieldset>\r\n\r\n  <select name=\"card-type\" class=\"ccjs-hidden-card-type\">\r\n    <option value=\"amex\" class=\"ccjs-amex\">American Express</option>\r\n    <option value=\"discover\" class=\"ccjs-discover\">Discover</option>\r\n    <option value=\"mastercard\" class=\"ccjs-mastercard\">MasterCard</option>\r\n    <option value=\"visa\" class=\"ccjs-visa\">Visa</option>\r\n    <option value=\"diners-club\" class=\"ccjs-diners-club\">Diners Club</option>\r\n    <option value=\"jcb\" class=\"ccjs-jcb\">JCB</option>\r\n    <!--<option value=\"laser\"    class=\"laser\">Laser</option>-->\r\n    <!--<option value=\"maestro\"  class=\"maestro\">Maestro</option>-->\r\n    <!--<option value=\"unionpay\" class=\"unionpay\">UnionPay</option>-->\r\n  </select>\r\n</div>\r\n\r\n<script src=\"/path/to/creditcardjs-v0.6.9.min.js\" async></script>","google":"UA-45799129-1","note":"Don't delete this file! It's used internally to help with page regeneration."}